{"fixtures": [{"id": 277, "started": false, "difficulty": 4, "opponent": 9, "is_home": true, "code": 1059978, "finished": false, "finished_provisional": false, "kickoff_time": "2020-02-28T20:00:00Z", "minutes": 0, "provisional_start_time": false, "team_a_score": null, "team_h_score": null, "event": 28, "team_a": 9, "team_h": 14}, {"id": 288, "started": false, "difficulty": 3, "opponent": 15, "is_home": false, "code": 1059989, "finished": false, "finished_provisional": false, "kickoff_time": "2020-03-07T15:00:00Z", "minutes": 0, "provisional_start_time": false, "team_a_score": null, "team_h_score": null, "event": 29, "team_a": 14, "team_h": 15}, {"id": 297, "started": false, "difficulty": 2, "opponent": 16, "is_home": true, "code": 1059998, "finished": false, "finished_provisional": false, "kickoff_time": "2020-03-14T15:00:00Z", "minutes": 0, "provisional_start_time": false, "team_a_score": null, "team_h_score": null, "event": 30, "team_a": 16, "team_h": 14}, {"id": 307, "started": false, "difficulty": 2, "opponent": 8, "is_home": true, "code": 1060008, "finished": false, "finished_provisional": false, "kickoff_time": "2020-03-21T15:00:00Z", "minutes": 0, "provisional_start_time": false, "team_a_score": null, "team_h_score": null, "event": 31, "team_a": 8, "team_h": 14}, {"id": 311, "started": false, "difficulty": 4, "opponent": 1, "is_home": false, "code": 1060013, "finished": false, "finished_provisional": false, "kickoff_time": "2020-04-04T14:00:00Z", "minutes": 0, "provisional_start_time": false, "team_a_score": null, "team_h_score": null, "event": 32, "team_a": 14, "team_h": 1}, {"id": 327, "started": false, "difficulty": 2, "opponent": 4, "is_home": true, "code": 1060028, "finished": false, "finished_provisional": false, "kickoff_time": "2020-04-11T14:00:00Z", "minutes": 0, "provisional_start_time": false, "team_a_score": null, "team_h_score": null, "event": 33, "team_a": 4, "team_h": 14}, {"id": 339, "started": false, "difficulty": 2, "opponent": 18, "is_home": false, "code": 1060040, "finished": false, "finished_provisional": false, "kickoff_time": "2020-04-18T14:00:00Z", "minutes": 0, "provisional_start_time": false, "team_a_score": null, "team_h_score": null, "event": 34, "team_a": 14, "team_h": 18}, {"id": 346, "started": false, "difficulty": 2, "opponent": 19, "is_home": true, "code": 1060047, "finished": false, "finished_provisional": false, "kickoff_time": "2020-04-25T14:00:00Z", "minutes": 0, "provisional_start_time": false, "team_a_score": null, "team_h_score": null, "event": 35, "team_a": 19, "team_h": 14}, {"id": 353, "started": false, "difficulty": 4, "opponent": 6, "is_home": false, "code": 1060054, "finished": false, "finished_provisional": false, "kickoff_time": "2020-05-02T14:00:00Z", "minutes": 0, "provisional_start_time": false, "team_a_score": null, "team_h_score": null, "event": 36, "team_a": 14, "team_h": 6}, {"id": 366, "started": false, "difficulty": 2, "opponent": 5, "is_home": true, "code": 1060067, "finished": false, "finished_provisional": false, "kickoff_time": "2020-05-09T14:00:00Z", "minutes": 0, "provisional_start_time": false, "team_a_score": null, "team_h_score": null, "event": 37, "team_a": 5, "team_h": 14}, {"id": 377, "started": false, "difficulty": 5, "opponent": 11, "is_home": false, "code": 1060078, "finished": false, "finished_provisional": false, "kickoff_time": "2020-05-17T14:00:00Z", "minutes": 0, "provisional_start_time": false, "team_a_score": null, "team_h_score": null, "event": 38, "team_a": 14, "team_h": 11}], "history": [{"id": 282, "detail": "LIV (A) 4-1", "event": 1, "assists": 0, "bonus": 0, "bps": 19, "clean_sheets": 0, "creativity": "0.0", "goals_conceded": 4, "goals_scored": 0, "ict_index": "3.0", "influence": "30.4", "minutes": 90, "own_goals": 0, "penalties_missed": 0, "penalties_saved": 0, "red_cards": 0, "saves": 4, "threat": "0.0", "yellow_cards": 0, "total_points": 1, "element": 282, "fixture": 1, "opponent_team": 10}, {"id": 810, "detail": "NEW (H) 3-1", "event": 2, "assists": 0, "bonus": 0, "bps": 15, "clean_sheets": 0, "creativity": "0.0", "goals_conceded": 1, "goals_scored": 0, "ict_index": "2.6", "influence": "25.6", "minutes": 90, "own_goals": 0, "penalties_missed": 0, "penalties_saved": 0, "red_cards": 0, "saves": 2, "threat": "0.0", "yellow_cards": 0, "total_points": 2, "element": 282, "fixture": 17, "opponent_team": 13}, {"id": 1341, "detail": "CHE (H) 2-3", "event": 3, "assists": 0, "bonus": 0, "bps": 19, "clean_sheets": 0, "creativity": "0.0", "goals_conceded": 3, "goals_scored": 0, "ict_index": "3.3", "influence": "32.8", "minutes": 90, "own_goals": 0, "penalties_missed": 0, "penalties_saved": 0, "red_cards": 0, "saves": 5, "threat": "0.0", "yellow_cards": 0, "total_points": 2, "element": 282, "fixture": 26, "opponent_team": 6}, {"id": 1872, "detail": "WHU (A) 2-0", "event": 4, "assists": 0, "bonus": 0, "bps": 19, "clean_sheets": 0, "creativity": "0.0", "goals_conceded": 2, "goals_scored": 0, "ict_index": "4.0", "influence": "39.8", "minutes": 90, "own_goals": 0, "penalties_missed": 0, "penalties_saved": 0, "red_cards": 0, "saves": 5, "threat": "0.0", "yellow_cards": 0, "total_points": 2, "element": 282, "fixture": 40, "opponent_team": 19}, {"id": 2406, "detail": "MCI (H) 3-2", "event": 5, "assists": 0, "bonus": 0, "bps": 23, "clean_sheets": 0, "creativity": "0.0", "goals_conceded": 2, "goals_scored": 0, "ict_index": "5.1", "influence": "51.0", "minutes": 90, "own_goals": 0, "penalties_missed": 0, "penalties_saved": 0, "red_cards": 0, "saves": 6, "threat": "0.0", "yellow_cards": 0, "total_points": 3, "element": 282, "fixture": 46, "opponent_team": 11}, {"id": 2947, "detail": "BUR (A) 2-0", "event": 6, "assists": 0, "bonus": 0, "bps": 17, "clean_sheets": 0, "creativity": "0.0", "goals_conceded": 2, "goals_scored": 0, "ict_index": "3.1", "influence": "31.2", "minutes": 90, "own_goals": 0, "penalties_missed": 0, "penalties_saved": 0, "red_cards": 0, "saves": 4, "threat": "0.0", "yellow_cards": 0, "total_points": 2, "element": 282, "fixture": 52, "opponent_team": 5}, {"id": 3490, "detail": "CRY (A) 2-0", "event": 7, "assists": 0, "bonus": 0, "bps": 0, "clean_sheets": 0, "creativity": "0.0", "goals_conceded": 0, "goals_scored": 0, "ict_index": "0.0", "influence": "0.0", "minutes": 0, "own_goals": 0, "penalties_missed": 0, "penalties_saved": 0, "red_cards": 0, "saves": 0, "threat": "0.0", "yellow_cards": 0, "total_points": 0, "element": 282, "fixture": 64, "opponent_team": 7}, {"id": 4038, "detail": "AVL (H) 1-5", "event": 8, "assists": 0, "bonus": 0, "bps": 0, "clean_sheets": 0, "creativity": "0.0", "goals_conceded": 0, "goals_scored": 0, "ict_index": "0.0", "influence": "0.0", "minutes": 0, "own_goals": 0, "penalties_missed": 0, "penalties_saved": 0, "red_cards": 0, "saves": 0, "threat": "0.0", "yellow_cards": 0, "total_points": 0, "element": 282, "fixture": 77, "opponent_team": 2}, {"id": 4591, "detail": "BOU (A) 0-0", "event": 9, "assists": 0, "bonus": 0, "bps": 23, "clean_sheets": 1, "creativity": "0.0", "goals_conceded": 0, "goals_scored": 0, "ict_index": "2.1", "influence": "21.4", "minutes": 90, "own_goals": 0, "penalties_missed": 0, "penalties_saved": 0, "red_cards": 0, "saves": 2, "threat": "0.0", "yellow_cards": 0, "total_points": 6, "element": 282, "fixture": 82, "opponent_team": 3}, {"id": 5148, "detail": "MUN (H) 1-3", "event": 10, "assists": 0, "bonus": 3, "bps": 54, "clean_sheets": 0, "creativity": "0.0", "goals_conceded": 3, "goals_scored": 0, "ict_index": "10.3", "influence": "102.8", "minutes": 90, "own_goals": 0, "penalties_missed": 0, "penalties_saved": 2, "red_cards": 0, "saves": 8, "threat": "0.0", "yellow_cards": 0, "total_points": 16, "element": 282, "fixture": 97, "opponent_team": 12}, {"id": 5706, "detail": "BHA (A) 2-0", "event": 11, "assists": 0, "bonus": 0, "bps": 14, "clean_sheets": 0, "creativity": "0.0", "goals_conceded": 2, "goals_scored": 0, "ict_index": "2.4", "influence": "24.0", "minutes": 90, "own_goals": 0, "penalties_missed": 0, "penalties_saved": 0, "red_cards": 0, "saves": 3, "threat": "0.0", "yellow_cards": 0, "total_points": 2, "element": 282, "fixture": 104, "opponent_team": 4}, {"id": 6265, "detail": "WAT (H) 0-2", "event": 12, "assists": 0, "bonus": 0, "bps": 9, "clean_sheets": 0, "creativity": "0.0", "goals_conceded": 2, "goals_scored": 0, "ict_index": "0.5", "influence": "4.8", "minutes": 90, "own_goals": 0, "penalties_missed": 0, "penalties_saved": 0, "red_cards": 0, "saves": 0, "threat": "0.0", "yellow_cards": 0, "total_points": 1, "element": 282, "fixture": 117, "opponent_team": 18}, {"id": 6826, "detail": "EVE (A) 0-2", "event": 13, "assists": 0, "bonus": 3, "bps": 37, "clean_sheets": 1, "creativity": "0.0", "goals_conceded": 0, "goals_scored": 0, "ict_index": "4.7", "influence": "47.4", "minutes": 90, "own_goals": 0, "penalties_missed": 0, "penalties_saved": 0, "red_cards": 0, "saves": 7, "threat": "0.0", "yellow_cards": 0, "total_points": 11, "element": 282, "fixture": 126, "opponent_team": 8}, {"id": 7388, "detail": "ARS (H) 2-2", "event": 14, "assists": 0, "bonus": 0, "bps": 13, "clean_sheets": 0, "creativity": "0.0", "goals_conceded": 2, "goals_scored": 0, "ict_index": "3.0", "influence": "30.0", "minutes": 90, "own_goals": 0, "penalties_missed": 0, "penalties_saved": 0, "red_cards": 0, "saves": 4, "threat": "0.0", "yellow_cards": 1, "total_points": 1, "element": 282, "fixture": 137, "opponent_team": 1}, {"id": 7954, "detail": "SOU (A) 2-1", "event": 15, "assists": 0, "bonus": 0, "bps": 16, "clean_sheets": 0, "creativity": "0.0", "goals_conceded": 2, "goals_scored": 0, "ict_index": "2.4", "influence": "23.6", "minutes": 90, "own_goals": 0, "penalties_missed": 0, "penalties_saved": 0, "red_cards": 0, "saves": 3, "threat": "0.0", "yellow_cards": 0, "total_points": 2, "element": 282, "fixture": 150, "opponent_team": 16}, {"id": 8521, "detail": "SHU (H) 1-2", "event": 16, "assists": 0, "bonus": 0, "bps": 12, "clean_sheets": 0, "creativity": "0.0", "goals_conceded": 2, "goals_scored": 0, "ict_index": "1.4", "influence": "14.0", "minutes": 90, "own_goals": 0, "penalties_missed": 0, "penalties_saved": 0, "red_cards": 0, "saves": 1, "threat": "0.0", "yellow_cards": 0, "total_points": 1, "element": 282, "fixture": 157, "opponent_team": 15}, {"id": 9092, "detail": "LEI (A) 1-1", "event": 17, "assists": 0, "bonus": 0, "bps": 11, "clean_sheets": 0, "creativity": "0.0", "goals_conceded": 1, "goals_scored": 0, "ict_index": "2.9", "influence": "28.8", "minutes": 90, "own_goals": 1, "penalties_missed": 0, "penalties_saved": 0, "red_cards": 0, "saves": 5, "threat": "0.0", "yellow_cards": 1, "total_points": 0, "element": 282, "fixture": 165, "opponent_team": 9}, {"id": 9649, "detail": "WOL (H) 1-2", "event": 18, "assists": 0, "bonus": 0, "bps": 12, "clean_sheets": 0, "creativity": "0.0", "goals_conceded": 2, "goals_scored": 0, "ict_index": "1.9", "influence": "19.2", "minutes": 90, "own_goals": 0, "penalties_missed": 0, "penalties_saved": 0, "red_cards": 0, "saves": 2, "threat": "0.0", "yellow_cards": 0, "total_points": 1, "element": 282, "fixture": 177, "opponent_team": 20}, {"id": 10192, "detail": "AVL (A) 1-0", "event": 19, "assists": 0, "bonus": 0, "bps": 11, "clean_sheets": 0, "creativity": "0.0", "goals_conceded": 1, "goals_scored": 0, "ict_index": "0.9", "influence": "8.6", "minutes": 90, "own_goals": 0, "penalties_missed": 0, "penalties_saved": 0, "red_cards": 0, "saves": 1, "threat": "0.0", "yellow_cards": 0, "total_points": 2, "element": 282, "fixture": 181, "opponent_team": 2}, {"id": 10774, "detail": "TOT (H) 2-2", "event": 20, "assists": 0, "bonus": 0, "bps": 16, "clean_sheets": 0, "creativity": "0.0", "goals_conceded": 2, "goals_scored": 0, "ict_index": "2.7", "influence": "27.4", "minutes": 90, "own_goals": 0, "penalties_missed": 0, "penalties_saved": 0, "red_cards": 0, "saves": 5, "threat": "0.0", "yellow_cards": 1, "total_points": 1, "element": 282, "fixture": 197, "opponent_team": 17}, {"id": 11360, "detail": "CRY (H) 1-1", "event": 21, "assists": 0, "bonus": 0, "bps": 11, "clean_sheets": 0, "creativity": "0.0", "goals_conceded": 1, "goals_scored": 0, "ict_index": "2.0", "influence": "19.6", "minutes": 90, "own_goals": 0, "penalties_missed": 0, "penalties_saved": 0, "red_cards": 0, "saves": 2, "threat": "0.0", "yellow_cards": 0, "total_points": 2, "element": 282, "fixture": 207, "opponent_team": 7}, {"id": 11948, "detail": "MUN (A) 4-0", "event": 22, "assists": 0, "bonus": 0, "bps": 8, "clean_sheets": 0, "creativity": "0.0", "goals_conceded": 4, "goals_scored": 0, "ict_index": "0.8", "influence": "8.2", "minutes": 90, "own_goals": 0, "penalties_missed": 0, "penalties_saved": 0, "red_cards": 0, "saves": 2, "threat": "0.0", "yellow_cards": 0, "total_points": 0, "element": 282, "fixture": 217, "opponent_team": 12}, {"id": 12550, "detail": "BOU (H) 1-0", "event": 23, "assists": 0, "bonus": 1, "bps": 24, "clean_sheets": 1, "creativity": "0.0", "goals_conceded": 0, "goals_scored": 0, "ict_index": "2.7", "influence": "27.0", "minutes": 90, "own_goals": 0, "penalties_missed": 0, "penalties_saved": 0, "red_cards": 0, "saves": 3, "threat": "0.0", "yellow_cards": 1, "total_points": 7, "element": 282, "fixture": 227, "opponent_team": 3}, {"id": 13179, "detail": "TOT (A) 2-1", "event": 24, "assists": 0, "bonus": 0, "bps": 13, "clean_sheets": 0, "creativity": "0.0", "goals_conceded": 2, "goals_scored": 0, "ict_index": "1.4", "influence": "14.0", "minutes": 90, "own_goals": 0, "penalties_missed": 0, "penalties_saved": 0, "red_cards": 0, "saves": 1, "threat": "0.0", "yellow_cards": 0, "total_points": 1, "element": 282, "fixture": 240, "opponent_team": 17}, {"id": 13832, "detail": "NEW (A) 0-0", "event": 25, "assists": 0, "bonus": 2, "bps": 33, "clean_sheets": 1, "creativity": "0.0", "goals_conceded": 0, "goals_scored": 0, "ict_index": "3.5", "influence": "34.6", "minutes": 90, "own_goals": 0, "penalties_missed": 0, "penalties_saved": 0, "red_cards": 0, "saves": 6, "threat": "0.0", "yellow_cards": 0, "total_points": 10, "element": 282, "fixture": 247, "opponent_team": 13}, {"id": 14453, "detail": "LIV (H) 0-1", "event": 26, "assists": 0, "bonus": 0, "bps": 19, "clean_sheets": 0, "creativity": "0.0", "goals_conceded": 1, "goals_scored": 0, "ict_index": "3.5", "influence": "35.4", "minutes": 90, "own_goals": 0, "penalties_missed": 0, "penalties_saved": 0, "red_cards": 0, "saves": 5, "threat": "0.0", "yellow_cards": 0, "total_points": 3, "element": 282, "fixture": 257, "opponent_team": 10}, {"id": 15140, "detail": "WOL (A) 3-0", "event": 27, "assists": 0, "bonus": 0, "bps": 19, "clean_sheets": 0, "creativity": "0.0", "goals_conceded": 3, "goals_scored": 0, "ict_index": "2.1", "influence": "21.2", "minutes": 90, "own_goals": 0, "penalties_missed": 0, "penalties_saved": 0, "red_cards": 0, "saves": 3, "threat": "0.0", "yellow_cards": 0, "total_points": 2, "element": 282, "fixture": 270, "opponent_team": 20}]}